{
  "cycle_id": "stories-3x-10d-apr2026",
  "start_date": "2026-04-24",
  "end_date": "2026-05-03",
  "slots": ["09:00", "14:00", "20:00"],
  "timezone": "America/Argentina/Buenos_Aires",
  "stories": [
    { "seq": 1,  "day": 1,  "slot": "manana",  "time": "09:00", "file": "fase2/travesias-f2-01.jpg", "category": "Travesías",      "caption": "El Delta del Paraná, a pocas horas de BA." },
    { "seq": 2,  "day": 1,  "slot": "tarde",   "time": "14:00", "file": "fase2/paseos-f2-01.jpg",    "category": "Paseos",         "caption": "Invitá a tu gente. El río está esperando." },
    { "seq": 3,  "day": 1,  "slot": "noche",   "time": "20:00", "file": "fase2/broker-f2-01.jpg",    "category": "Broker",         "caption": "¿Soñás con tu propio velero?" },
    { "seq": 4,  "day": 2,  "slot": "manana",  "time": "09:00", "file": "fase2/escuela-f2-01.jpg",   "category": "Escuela",        "caption": "Maniobras reales desde el primer día." },
    { "seq": 5,  "day": 2,  "slot": "tarde",   "time": "14:00", "file": "fase2/services-f2-01.jpg",  "category": "Services",       "caption": "Equipo propio. Trabajo a conciencia." },
    { "seq": 6,  "day": 2,  "slot": "noche",   "time": "20:00", "file": "fase2/quienes-f2-01.jpg",   "category": "¿Quiénes somos?","caption": "Navegamos, enseñamos, cuidamos tu barco." },
    { "seq": 7,  "day": 3,  "slot": "manana",  "time": "09:00", "file": "fase2/travesias-f2-02.jpg", "category": "Travesías",      "caption": "Martín García: la isla del río." },
    { "seq": 8,  "day": 3,  "slot": "tarde",   "time": "14:00", "file": "fase2/paseos-f2-02.jpg",    "category": "Paseos",         "caption": "Una tarde diferente en familia." },
    { "seq": 9,  "day": 3,  "slot": "noche",   "time": "20:00", "file": "fase2/broker-f2-02.jpg",    "category": "Broker",         "caption": "El próximo velero puede ser tuyo." },
    { "seq": 10, "day": 4,  "slot": "manana",  "time": "09:00", "file": "fase2/escuela-f2-02.jpg",   "category": "Escuela",        "caption": "Aprendés navegando, no leyendo." },
    { "seq": 11, "day": 4,  "slot": "tarde",   "time": "14:00", "file": "fase2/services-f2-02.jpg",  "category": "Services",       "caption": "Casco, quilla y obra viva en condiciones." },
    { "seq": 12, "day": 4,  "slot": "noche",   "time": "20:00", "file": "fase2/quienes-f2-02.jpg",   "category": "¿Quiénes somos?","caption": "El Río de la Plata es nuestro lugar." },
    { "seq": 13, "day": 5,  "slot": "manana",  "time": "09:00", "file": "fase2/travesias-f2-03.jpg", "category": "Travesías",      "caption": "Fondear y quedarse a dormir bajo las estrellas." },
    { "seq": 14, "day": 5,  "slot": "tarde",   "time": "14:00", "file": "fase2/paseos-f2-03.jpg",    "category": "Paseos",         "caption": "Tres horas en el río. Sin experiencia previa." },
    { "seq": 15, "day": 5,  "slot": "noche",   "time": "20:00", "file": "fase2/broker-f2-03.jpg",    "category": "Broker",         "caption": "Compramos y vendemos con criterio náutico." },
    { "seq": 16, "day": 6,  "slot": "manana",  "time": "09:00", "file": "fase2/escuela-f2-03.jpg",   "category": "Escuela",        "caption": "En todas las condiciones. Eso se aprende." },
    { "seq": 17, "day": 6,  "slot": "tarde",   "time": "14:00", "file": "fase2/services-f2-03.jpg",  "category": "Services",       "caption": "Tu embarcación siempre lista para navegar." },
    { "seq": 18, "day": 6,  "slot": "noche",   "time": "20:00", "file": "fase2/quienes-f2-03.jpg",   "category": "¿Quiénes somos?","caption": "Antes de cada salida, estamos con vos." },
    { "seq": 19, "day": 7,  "slot": "manana",  "time": "09:00", "file": "fase2/travesias-f2-04.jpg", "category": "Travesías",      "caption": "Navegar en flota. Una experiencia única." },
    { "seq": 20, "day": 7,  "slot": "tarde",   "time": "14:00", "file": "fase2/paseos-f2-04.jpg",    "category": "Paseos",         "caption": "El skyline de Buenos Aires desde cubierta." },
    { "seq": 21, "day": 7,  "slot": "noche",   "time": "20:00", "file": "fase2/broker-f2-04.jpg",    "category": "Broker",         "caption": "Tu barco ideal, en el lugar correcto." },
    { "seq": 22, "day": 8,  "slot": "manana",  "time": "09:00", "file": "fase2/escuela-f2-04.jpg",   "category": "Escuela",        "caption": "Rumbo propio. Con brújula incluida." },
    { "seq": 23, "day": 8,  "slot": "tarde",   "time": "14:00", "file": "fase2/services-f2-04.jpg",  "category": "Services",       "caption": "Varadero con experiencia náutica real." },
    { "seq": 24, "day": 8,  "slot": "noche",   "time": "20:00", "file": "fase2/quienes-f2-04.jpg",   "category": "¿Quiénes somos?","caption": "Celebramos cada travesía completada." },
    { "seq": 25, "day": 9,  "slot": "manana",  "time": "09:00", "file": "fase2/travesias-f2-05.jpg", "category": "Travesías",      "caption": "El Río de la Plata en todas sus caras." },
    { "seq": 26, "day": 9,  "slot": "tarde",   "time": "14:00", "file": "fase2/paseos-f2-05.jpg",    "category": "Paseos",         "caption": "Mate, viento y río abierto." },
    { "seq": 27, "day": 9,  "slot": "noche",   "time": "20:00", "file": "fase2/broker-f2-05.jpg",    "category": "Broker",         "caption": "Consultá nuestro stock disponible." },
    { "seq": 28, "day": 10, "slot": "manana",  "time": "09:00", "file": "fase2/escuela-f2-05.jpg",   "category": "Escuela",        "caption": "Un equipo que aprende junto en el río." },
    { "seq": 29, "day": 10, "slot": "tarde",   "time": "14:00", "file": "fase2/services-f2-05.jpg",  "category": "Services",       "caption": "Mantenimiento integral, dentro y fuera." },
    { "seq": 30, "day": 10, "slot": "noche",   "time": "20:00", "file": "fase2/quienes-f2-05.jpg",   "category": "¿Quiénes somos?","caption": "Costanera Norte, frente al Aeroparque." }
  ]
}
